<?xml version="1.0"?>
<?xml-stylesheet type="text/xsl" href="ont-type.xsl"?>
<dsl>
 <provenance name="TRIPS"/>
 <syntax name="ont::count-pred-3p-templ">
 <template-call template="ont::count-pred-3p-templ" />
 <syn-feats>
  <feat name="mass">count</feat>
  <feat name="case">
  <or>
   sub
   obj
  </or>
  </feat>
  <feat name="agr">|3p|</feat>
  <feat name="sort">pred</feat>
 </syn-feats>
 </syntax>
 <sense>
 <morph>
  <pos pos="n" />
  <word first-word="assets" />
  <forms>
   -NONE
  </forms>
 </morph>
 <relation label="inherit">
  ont::assets
  ont::count-pred-3p-templ
 </relation>
 </sense>
 <sense>
 <morph>
  <pos pos="n" />
  <word first-word="belongings" />
  <forms>
   -NONE
  </forms>
 </morph>
 <example text="don't steal my belongings">
  <provenance name="TRIPS"/>
 </example>
 <relation label="inherit">
  ont::assets
  ont::count-pred-3p-templ
 </relation>
 </sense>
 <sense>
 <morph>
  <pos pos="n" />
  <word first-word="comms" />
  <forms>
   -NONE
  </forms>
 </morph>
 <comment>
  &quot;LOU-SENT-ENTRY&quot;
 </comment>
 <relation label="inherit">
  ont::info-medium
  ont::count-pred-3p-templ
 </relation>
 </sense>
 <sense>
 <morph>
  <pos pos="n" />
  <word first-word="directions" />
  <forms>
   -NONE
  </forms>
 </morph>
 <comment>
  &quot;LF-RESTRUCTURING&quot;
 </comment>
 <relation label="inherit">
  ont::recipe
  ont::count-pred-3p-templ
 </relation>
 </sense>
 <sense>
 <morph>
  <pos pos="n" />
  <word first-word="drapes" />
 </morph>
 <relation label="inherit">
  ont::covering
  ont::count-pred-3p-templ
 </relation>
 </sense>
 <sense>
 <morph>
  <pos pos="n" />
  <word first-word="electronics" />
  <forms>
   -NONE
  </forms>
 </morph>
 <comment>
  &quot;HTML-PURCHASING-CORPUS&quot;
 </comment>
 <relation label="inherit">
  ont::discipline
  ont::count-pred-3p-templ
 </relation>
 </sense>
 <sense>
 <morph>
  <pos pos="n" />
  <word first-word="electronics" />
  <forms>
   -NONE
  </forms>
 </morph>
 <comment>
  &quot;OFFICE&quot;
 </comment>
 <relation label="inherit">
  ont::device
  ont::count-pred-3p-templ
 </relation>
 </sense>
 <sense>
 <morph>
  <pos pos="n" />
  <word first-word="goods" />
  <forms>
   -NONE
  </forms>
 </morph>
 <relation label="inherit">
  ont::commodity
  ont::count-pred-3p-templ
 </relation>
 </sense>
 <sense>
 <morph>
  <pos pos="n" />
  <word first-word="grapefruit" />
 </morph>
 <example text="take two grapefruit">
  <provenance name="TRIPS"/>
 </example>
 <relation label="inherit">
  ont::fruit
  ont::count-pred-3p-templ
 </relation>
 </sense>
 <sense>
 <morph>
  <pos pos="n" />
  <word first-word="instructions" />
  <forms>
   -NONE
  </forms>
 </morph>
 <comment>
  &quot;LF-RESTRUCTURING&quot;
 </comment>
 <relation label="inherit">
  ont::recipe
  ont::count-pred-3p-templ
 </relation>
 </sense>
 <sense>
 <morph>
  <pos pos="n" />
  <word first-word="minutes" />
  <forms>
   -NONE
  </forms>
 </morph>
 <comment>
  &quot;PQ0134&quot;
 </comment>
 <example text="the minutes of the meeting">
  <provenance name="TRIPS"/>
 </example>
 <relation label="inherit">
  ont::chronicle
  ont::count-pred-3p-templ
 </relation>
 </sense>
 <sense>
 <morph>
  <pos pos="n" />
  <word first-word="others" />
  <forms>
   -NONE
  </forms>
 </morph>
 <comment>
  &quot;S14&quot;
 </comment>
 <relation label="inherit">
  ont::other
  ont::count-pred-3p-templ
 </relation>
 </sense>
 <sense>
 <morph>
  <pos pos="n" />
  <word first-word="persons" />
  <forms>
   -NONE
  </forms>
 </morph>
 <relation label="inherit">
  ont::person
  ont::count-pred-3p-templ
 </relation>
 </sense>
 <sense>
 <morph>
  <pos pos="n" />
  <word first-word="police" />
  <forms>
   -NONE
  </forms>
 </morph>
 <relation label="inherit">
  ont::professional
  ont::count-pred-3p-templ
 </relation>
 </sense>
 <sense>
 <morph>
  <pos pos="n" />
  <word first-word="potatos" />
  <forms>
   -NONE
  </forms>
 </morph>
 <relation label="inherit">
  ont::vegetable
  ont::count-pred-3p-templ
 </relation>
 </sense>
 <sense>
 <morph>
  <pos pos="n" />
  <word first-word="proceedings" />
 </morph>
 <example text="conference proceedings">
  <provenance name="TRIPS"/>
 </example>
 <relation label="inherit">
  ont::info-medium
  ont::count-pred-3p-templ
 </relation>
 </sense>
 <sense>
 <morph>
  <pos pos="n" />
  <word first-word="supplies" />
  <forms>
   -NONE
  </forms>
 </morph>
 <relation label="inherit">
  ont::commodity
  ont::count-pred-3p-templ
 </relation>
 </sense>
 <sense>
 <morph>
  <pos pos="n" />
  <word first-word="term" />
 </morph>
 <comment>
  &quot;CALOY3&quot;
 </comment>
 <example text="he agreed to the terms of the contract">
  <provenance name="TRIPS"/>
 </example>
 <relation label="inherit">
  ont::requirements
  ont::count-pred-3p-templ
 </relation>
 </sense>
 <sense>
 <morph>
  <pos pos="n" />
  <word first-word="tomatos" />
  <forms>
   -NONE
  </forms>
 </morph>
 <relation label="inherit">
  ont::fruit
  ont::count-pred-3p-templ
 </relation>
 </sense>
</dsl>
