<?xml version="1.0"?>
<?xml-stylesheet type="text/xsl" href="ont-type.xsl"?>
<dsl>
 <provenance name="TRIPS"/>
 <syntax name="ont::binary-constraint-s-or-np-general-templ">
 <template-call template="ont::binary-constraint-s-or-np-general-templ" />
 <syn-sem>
  <syn-sem-map syn-arg="subcat" syn-cat="?" head-word="sc" sem-role="ont::val"/>
  <syn-sem-map syn-arg="argument" syn-cat="?" head-word="ag" sem-role="ont::of"/>
 </syn-sem>
 <syn-feats>
  <feat name="atype">
  <or>
   pre
   post
  </or>
  </feat>
  <feat name="sort">binary-constraint</feat>
 </syn-feats>
 </syntax>
</dsl>
