<?xml version="1.0" encoding="UTF-8"?>
<!DOCTYPE ONTTYPE SYSTEM "onttype.dtd">
<ONTTYPE name="prescribing" parent="giving" modified="Mon Oct 15 01:43:56 2018">
<SEM fltype="situation">
<FEATURES type="prescribing" cause="agentive" iobj="recipient" aspect="dynamic" container="-" information="mental-construct" intentional="-" />
</SEM>
<ARGUMENT role="result" optionality="optional" fltype="(? tc362359 abstr-obj)" />
<ARGUMENT role="affected-result" optionality="required" fltype="(? tc2622 phys-obj abstr-obj)" />
<ARGUMENT role="affected" optionality="required" fltype="(? tc162158 phys-obj abstr-obj)">
<FEATURES tangible="+" />
</ARGUMENT>
<ARGUMENT role="agent" optionality="required" fltype="(? ag68691 phys-obj abstr-obj)">
<FEATURES intentional="+" tangible="+" />
</ARGUMENT>
<ARGUMENT role="formal" optionality="essential" fltype="(? tt687 phys-obj abstr-obj)">
<FEATURES intentional="-" />
</ARGUMENT>
<WORD name="prescribe" />
</ONTTYPE>
