<?xml version="1.0" encoding="UTF-8"?>
<!DOCTYPE ONTTYPE SYSTEM "onttype.dtd">
<ONTTYPE name="calc-add" parent="calculation" modified="Tue Aug  1 01:46:04 2017">
<SEM fltype="situation">
<FEATURES type="calc-add" trajectory="-" cause="mental" aspect="dynamic" container="-" information="mental-construct" intentional="-" />
</SEM>
<ARGUMENT role="agent" optionality="essential" fltype="(? agt3233 phys-obj abstr-obj)">
<FEATURES intentional="+" />
</ARGUMENT>
<ARGUMENT role="neutral" optionality="required" fltype="(? th63231 phys-obj abstr-obj situation)" />
<ARGUMENT role="source" optionality="optional" fltype="?!type" />
<ARGUMENT role="beneficiary" optionality="optional" fltype="(? cau13126 phys-obj)" />
<ARGUMENT role="result" optionality="optional" fltype="(? cau23125 situation abstr-obj phys-obj)" />
<ARGUMENT role="affected" optionality="optional" fltype="(? cau3a3124 situation abstr-obj phys-obj)" />
<ARGUMENT role="norole" optionality="optional" fltype="?!type" />
<ARGUMENT role="formal" optionality="required" fltype="abstr-obj">
<FEATURES type="mathematical-term" />
</ARGUMENT>
<ARGUMENT role="formal1" optionality="optional" fltype="abstr-obj">
<FEATURES type="mathematical-term" />
</ARGUMENT>
<WORD name="add" />
<MAPPING to="wordnet" name="add%2:31:00::" url="http://wordnetweb.princeton.edu/perl/webwn?s=add&amp;i=4&amp;o6=1" />
</ONTTYPE>
