<?xml version="1.0" encoding="UTF-8"?>
<!DOCTYPE ONTTYPE SYSTEM "onttype.dtd">
<ONTTYPE name="goal-reln" parent="path" modified="Sat Jun  2 01:43:26 2018">
<SEM fltype="abstr-obj">
<FEATURES type="goal-reln" />
</SEM>
<ARGUMENT role="ground" optionality="essential" fltype="(? val468 phys-obj situation abstr-obj)" />
<ARGUMENT role="figure" optionality="essential" fltype="(? of467 phys-obj situation abstr-obj)" />
<CHILD name="goal-as-containment" />
<CHILD name="goal-as-on" />
<CHILD name="resulting-state" />
<CHILD name="to" />
<CHILD name="to-loc" />
</ONTTYPE>
