<?xml version="1.0" encoding="UTF-8"?>
<!DOCTYPE ONTTYPE SYSTEM "onttype.dtd">
<ONTTYPE name="identification" parent="information-function-object" modified="Wed Aug  3 01:42:37 2016">
<SEM fltype="abstr-obj">
<FEATURES type="identification" container="+" intentional="-" information="information-content" />
</SEM>
<ARGUMENT role="figure" optionality="essential" fltype="(? lof phys-obj abstr-obj)" />
<WORD name="i_d" />
<WORD name="code" />
<WORD name="id" />
<WORD name="identifier" />
<WORD name="identity" />
<WORD name="key" />
<CHILD name="id-number" />
<CHILD name="location-id" />
<CHILD name="name" />
<CHILD name="password" />
<CHILD name="username" />
</ONTTYPE>
