<?xml version="1.0" encoding="UTF-8"?>
<!DOCTYPE ONTTYPE SYSTEM "onttype.dtd">
<ONTTYPE name="vehicle" parent="manufactured-object" modified="Sun Jun 10 01:43:42 2018">
<SEM fltype="phys-obj">
<FEATURES type="vehicle" container="(? fcont + -)" mobility="self-moving" object-function="vehicle" origin="artifact" tangible="+" />
</SEM>
<WORD name="boat" />
<WORD name="metro" />
<WORD name="ship" />
<WORD name="subway" />
<WORD name="train" />
<WORD name="tram" />
<WORD name="transport" />
<WORD name="transportation" />
<WORD name="vehicle" />
<MAPPING to="wordnet" name="conveyance%1:06:00::" url="http://wordnetweb.princeton.edu/perl/webwn?s=conveyance&amp;i=2&amp;o6=1" />
<MAPPING to="wordnet" name="vehicle%1:06:00::" url="http://wordnetweb.princeton.edu/perl/webwn?s=vehicle&amp;i=0&amp;o6=1" />
<CHILD name="air-vehicle" />
<CHILD name="land-vehicle" />
<CHILD name="vehicle-part" />
</ONTTYPE>
