<?xml version="1.0" encoding="UTF-8"?>
<?xml-stylesheet type="text/xsl" href="../style/onttype.xsl"?>
<!DOCTYPE ONTTYPE SYSTEM "onttype.dtd">
<ONTTYPE name="skip-action" parent="omit" modified="Fri Dec  6 06:43:37 2019">
<SEM fltype="situation">
<FEATURES type="skip-action" time-span="atomic" aspect="bounded" trajectory="-" cause="agentive" tangible="+" container="-" intentional="-" />
</SEM>
<ARGUMENT role="source" optionality="optional" fltype="(? src863 abstr-obj)" />
<ARGUMENT role="result" optionality="optional" fltype="(? res862142 abstr-obj)">
<FEATURES intentional="-" />
</ARGUMENT>
<ARGUMENT role="agent" optionality="required" fltype="(? agt860143 phys-obj abstr-obj)">
<FEATURES intentional="+" tangible="+" />
</ARGUMENT>
<ARGUMENT role="affected1" optionality="optional" fltype="(? transform-aff1848 phys-obj abstr-obj)" />
<ARGUMENT role="affected" optionality="required" fltype="(? th24852135 situation phys-obj abstr-obj)">
<FEATURES tangible="+" />
</ARGUMENT>
<ARGUMENT role="formal" optionality="essential" fltype="(? ttype895158 abstr-obj)">
<FEATURES intentional="-" />
</ARGUMENT>
<WORD name="skip" />
</ONTTYPE>
