<?xml version="1.0" encoding="UTF-8"?>
<!DOCTYPE ONTTYPE SYSTEM "onttype.dtd">
<ONTTYPE name="mental-psychological-illness-or-disorder" parent="event-type" modified="Mon Jun 25 01:44:18 2018">
<SEM fltype="situation">
<FEATURES type="mental-psychological-illness-or-disorder" intentional="-" container="-" information="mental-construct" />
</SEM>
<MAPPING to="wordnet" name="mental_illness%1:26:00::" url="http://wordnetweb.princeton.edu/perl/webwn?s=mental+illness&amp;i=0&amp;o6=1" />
<MAPPING to="wordnet" name="mental_disorder%1:26:00::" url="http://wordnetweb.princeton.edu/perl/webwn?s=mental+disorder&amp;i=0&amp;o6=1" />
<CHILD name="addiction" />
<CHILD name="amnesia" />
<CHILD name="anxiety" />
<CHILD name="depression" />
<CHILD name="eating-disorder" />
<CHILD name="insanity" />
<CHILD name="mania" />
<CHILD name="nervous-disorder" />
<CHILD name="phobia" />
</ONTTYPE>
