<?xml version="1.0" encoding="UTF-8"?>
<!DOCTYPE ONTTYPE SYSTEM "onttype.dtd">
<ONTTYPE name="mathematical-term" parent="abstract-object-nontemporal" modified="Fri May 20 01:42:53 2016">
<SEM fltype="abstr-obj">
<FEATURES gradability="-" type="abstract-object-nontemporal" />
</SEM>
<ARGUMENT role="of" optionality="essential" fltype="abstr-obj">
<FEATURES measure-function="term" />
</ARGUMENT>
<ARGUMENT role="val" optionality="essential" fltype="abstr-obj" />
<WORD name="argument" />
<WORD name="constant" />
<WORD name="denominator" />
<WORD name="derivative" />
<WORD name="differentiation" />
<WORD name="equation" />
<WORD name="expression" />
<WORD name="factor" />
<WORD name="formula" />
<WORD name="fraction" />
<WORD name="multiplication" />
<WORD name="numerator" />
<WORD name="parameter" />
<WORD name="simplification" />
<WORD name="subtraction" />
<WORD name="term" />
</ONTTYPE>
