<?xml version="1.0" encoding="UTF-8"?>
<!DOCTYPE ONTTYPE SYSTEM "onttype.dtd">
<ONTTYPE name="decrease-completely" parent="decrease" modified="Thu Jan  5 01:44:22 2017">
<SEM fltype="situation">
<FEATURES type="decrease-completely" trajectory="-" cause="agentive" aspect="dynamic" container="-" information="mental-construct" intentional="-" />
</SEM>
<ARGUMENT role="agent" optionality="optional" fltype="(? cs3440 phys-obj abstr-obj situation)" />
<ARGUMENT role="result" optionality="optional" fltype="(? res343964 abstr-obj phys-obj situation)" />
<ARGUMENT role="affected" optionality="required" fltype="(? th24343863 situation phys-obj abstr-obj)" />
<ARGUMENT role="formal" optionality="optional" fltype="(? cl3337 abstr-obj situation time)" />
<ARGUMENT role="beneficiary" optionality="optional" fltype="(? cau13126 phys-obj)" />
<ARGUMENT role="affected1" optionality="optional" fltype="(? transform-aff13434 phys-obj abstr-obj)" />
<WORD name="deplete" />
<MAPPING to="wordnet" name="consume%2:34:01::" url="http://wordnetweb.princeton.edu/perl/webwn?s=consume&amp;i=4&amp;o6=1" />
<MAPPING to="wordnet" name="exhaust%2:30:00::" url="http://wordnetweb.princeton.edu/perl/webwn?s=exhaust&amp;i=5&amp;o6=1" />
</ONTTYPE>
