<?xml version="1.0" encoding="UTF-8"?>
<?xml-stylesheet type="text/xsl" href="../style/onttype.xsl"?>
<!DOCTYPE ONTTYPE SYSTEM "onttype.dtd">
<ONTTYPE name="cause-surround" parent="cause-position" modified="Fri Dec  6 06:43:13 2019">
<SEM fltype="situation">
<FEATURES type="cause-surround" cause="force" aspect="dynamic" tangible="+" container="-" intentional="-" />
</SEM>
<ARGUMENT role="affected1" optionality="optional" fltype="?!type" />
<ARGUMENT role="affected-result" optionality="essential" fltype="?!type" />
<ARGUMENT role="result" optionality="optional" fltype="abstr-obj" />
<ARGUMENT role="affected" optionality="essential" fltype="(? cau5431 abstr-obj phys-obj situation)">
<FEATURES tangible="+" />
</ARGUMENT>
<ARGUMENT role="agent" optionality="essential" fltype="(? cau64321 abstr-obj phys-obj situation)">
<FEATURES tangible="+" />
</ARGUMENT>
<MAPPING to="wordnet" name="enclose%2:35:00::" url="http://wordnetweb.princeton.edu/perl/webwn?s=enclose&amp;i=2&amp;o6=1" />
</ONTTYPE>
