<?xml version="1.0" encoding="UTF-8"?>
<!DOCTYPE ONTTYPE SYSTEM "onttype.dtd">
<ONTTYPE name="location" parent="geo-object" modified="Wed Sep  7 01:42:25 2016">
<SEM fltype="phys-obj">
<FEATURES type="location" object-function="spatial-object" form="geographical-object" origin="non-living" />
</SEM>
<ARGUMENT role="figure" optionality="optional" fltype="(? lof3181 situation phys-obj)" />
<WORD name="way_point" />
<WORD name="angle" />
<WORD name="campus" />
<WORD name="direction" />
<WORD name="location" />
<WORD name="placement" />
<WORD name="position" />
<WORD name="somewhere" />
<WORD name="stop" />
<WORD name="there" />
<WORD name="waypoint" />
<WORD name="where" />
<WORD name="where" />
<WORD name="wherever" />
<CHILD name="coordinate" />
<CHILD name="destination" />
<CHILD name="loc-as-defined-by-reln-to-ground" />
<CHILD name="loc-as-point" />
<CHILD name="location-by-description" />
<CHILD name="location-reln" />
<CHILD name="object-dependent-location" />
<CHILD name="place" />
<CHILD name="point" />
<CHILD name="setting" />
<CHILD name="specific-loc" />
<CHILD name="wh-location" />
</ONTTYPE>
