<?xml version="1.0" encoding="UTF-8"?>
<!DOCTYPE ONTTYPE SYSTEM "onttype.dtd">
<ONTTYPE name="negative-body-condition-scale" parent="body-condition-scale" modified="Sat Nov 25 01:44:31 2017">
<SEM fltype="abstr-obj">
<FEATURES type="negative-body-condition-scale" />
</SEM>
<ARGUMENT role="extent" optionality="optional" fltype="?!type" />
<ARGUMENT role="ground" optionality="optional" fltype="?!type" />
<ARGUMENT role="figure" optionality="required" fltype="?!type" />
<CHILD name="feebleness-scale" />
<CHILD name="illness-scale" />
<CHILD name="restlessness-scale" />
</ONTTYPE>
