<?xml version="1.0" encoding="UTF-8"?>
<!DOCTYPE ONTTYPE SYSTEM "onttype.dtd">
<ONTTYPE name="incoming" parent="direction-val" modified="Mon Nov  6 01:42:52 2017">
<SEM fltype="abstr-obj">
<FEATURES type="incoming" intentional="-" information="-" container="-" />
</SEM>
<ARGUMENT role="norole" optionality="optional" fltype="?!type" />
<ARGUMENT role="standard" optionality="optional" fltype="?!type" />
<ARGUMENT role="reason" optionality="optional" fltype="(? pi591 phys-obj abstr-obj situation)" />
<ARGUMENT role="affected" optionality="optional" fltype="(? aff590 phys-obj abstr-obj situation)" />
<ARGUMENT role="neutral" optionality="optional" fltype="(? pvt589 phys-obj abstr-obj situation)" />
<ARGUMENT role="neutral1" optionality="optional" fltype="?!type" />
<ARGUMENT role="formal" optionality="optional" fltype="situation" />
<ARGUMENT role="scale" optionality="essential" fltype="?!type" />
<ARGUMENT role="figure" optionality="optional" fltype="(? of608 phys-obj situation abstr-obj)" />
<ARGUMENT role="ground" optionality="optional" fltype="(? val609 phys-obj situation abstr-obj)" />
<WORD name="inbound" />
<WORD name="incoming" />
<MAPPING to="wordnet" name="inbound%5:00:00:incoming:00" url="http://wordnetweb.princeton.edu/perl/webwn?s=inbound&amp;i=0&amp;o6=1" />
<MAPPING to="wordnet" name="incoming%3:00:00::" url="http://wordnetweb.princeton.edu/perl/webwn?s=incoming&amp;i=1&amp;o6=1" />
</ONTTYPE>
