<?xml version="1.0" encoding="UTF-8"?>
<!DOCTYPE ONTTYPE SYSTEM "onttype.dtd">
<ONTTYPE name="participate-attend" parent="event-of-causation" modified="Wed Sep 28 01:43:29 2016">
<SEM fltype="situation">
<FEATURES type="participate-attend" cause="force" aspect="dynamic" container="-" information="mental-construct" intentional="-" />
</SEM>
<ARGUMENT role="affected" optionality="essential" fltype="(? cau53130 abstr-obj phys-obj situation)" />
<ARGUMENT role="beneficiary" optionality="optional" fltype="(? cau13126 phys-obj)" />
<ARGUMENT role="result" optionality="optional" fltype="(? cau23125 situation abstr-obj phys-obj)" />
<ARGUMENT role="agent" optionality="required" fltype="phys-obj">
<FEATURES intentional="+" />
</ARGUMENT>
<ARGUMENT role="neutral" optionality="required" fltype="(? xx3494 situation abstr-obj)" />
<MAPPING to="wordnet" name="attend%2:42:00::" url="http://wordnetweb.princeton.edu/perl/webwn?s=attend&amp;i=0&amp;o6=1" />
<MAPPING to="wordnet" name="participate%2:41:00::" url="http://wordnetweb.princeton.edu/perl/webwn?s=participate&amp;i=0&amp;o6=1" />
</ONTTYPE>
