<?xml version="1.0" encoding="UTF-8"?>
<?xml-stylesheet type="text/xsl" href="../style/onttype.xsl"?>
<!DOCTYPE ONTTYPE SYSTEM "onttype.dtd">
<ONTTYPE name="early-in-process" parent="scheduled-time-modifier" modified="Mon Oct 21 01:43:22 2019">
<SEM fltype="abstr-obj">
<FEATURES type="early-in-process" />
</SEM>
<ARGUMENT role="figure" optionality="essential" fltype="(? of514 phys-obj situation time)" />
<ARGUMENT role="compar" optionality="optional" fltype="?!type" />
<ARGUMENT role="norole" optionality="optional" fltype="?!type" />
<ARGUMENT role="neutral1" optionality="optional" fltype="?!type" />
<ARGUMENT role="neutral" optionality="optional" fltype="?!type" />
<ARGUMENT role="ground" optionality="essential" fltype="?!type" />
<ARGUMENT role="scale" optionality="essential" fltype="?!type" />
<ARGUMENT role="standard" optionality="essential" fltype="?!type" />
<WORD name="early" />
<WORD name="early" />
<MAPPING to="wordnet" name="early%3:00:02::" url="http://wordnetweb.princeton.edu/perl/webwn?s=early&amp;i=1&amp;o6=1" />
<MAPPING to="wordnet" name="early%4:02:00::" url="http://wordnetweb.princeton.edu/perl/webwn?s=early&amp;i=7&amp;o6=1" />
</ONTTYPE>
