<?xml version="1.0" encoding="UTF-8"?>
<?xml-stylesheet type="text/xsl" href="../style/onttype.xsl"?>
<!DOCTYPE ONTTYPE SYSTEM "onttype.dtd">
<ONTTYPE name="borrow" parent="commerce-collect" modified="Mon Mar 30 05:46:26 2020">
<SEM fltype="situation">
<FEATURES type="borrow" aspect="dynamic" trajectory="-" cause="agentive" tangible="+" container="-" intentional="-" />
</SEM>
<ARGUMENT role="affected-result" optionality="optional" fltype="?!type" />
<ARGUMENT role="agent" optionality="required" fltype="(? ag62851 abstr-obj phys-obj)">
<FEATURES intentional="+" tangible="+" />
</ARGUMENT>
<ARGUMENT role="extent" optionality="optional" fltype="abstr-obj">
<FEATURES scale="money-scale" />
</ARGUMENT>
<ARGUMENT role="affected" optionality="required" fltype="(? th1169157 phys-obj abstr-obj situation)">
<FEATURES tangible="+" />
</ARGUMENT>
<ARGUMENT role="neutral" optionality="optional" fltype="abstr-obj">
<FEATURES scale="money-scale" />
</ARGUMENT>
<ARGUMENT role="result" optionality="optional" fltype="(? rcp69258 abstr-obj)">
<FEATURES intentional="+" />
</ARGUMENT>
<ARGUMENT role="source" optionality="optional" fltype="(? sc693 phys-obj abstr-obj)" />
<WORD name="borrow" />
<MAPPING to="wordnet" name="borrow%2:40:00::" url="http://wordnetweb.princeton.edu/perl/webwn?s=borrow&amp;i=0&amp;o6=1" />
</ONTTYPE>
