<?xml version="1.0" encoding="UTF-8"?>
<!DOCTYPE ONTTYPE SYSTEM "onttype.dtd">
<ONTTYPE name="speech-act" parent="any-sem" modified="Mon Mar 20 01:43:22 2017">
<SEM fltype="nil">
<FEATURES type="speech-act" />
</SEM>
<ARGUMENT role="content" optionality="required" fltype="?!type" />
<CHILD name="goodbye" />
<CHILD name="sa_ack" />
<CHILD name="sa_apologize" />
<CHILD name="sa_close" />
<CHILD name="sa_confirm" />
<CHILD name="sa_discourse-manage" />
<CHILD name="sa_discourse-signal" />
<CHILD name="sa_evaluation" />
<CHILD name="sa_expressive" />
<CHILD name="sa_go-offline" />
<CHILD name="sa_go-online" />
<CHILD name="sa_greet" />
<CHILD name="sa_nolo-comprendez" />
<CHILD name="sa_question" />
<CHILD name="sa_reject" />
<CHILD name="sa_request" />
<CHILD name="sa_suggest" />
<CHILD name="sa_tell" />
<CHILD name="sa_thank" />
<CHILD name="sa_welcome" />
</ONTTYPE>
