<?xml version="1.0" encoding="UTF-8"?>
<!DOCTYPE ONTTYPE SYSTEM "onttype.dtd">
<ONTTYPE name="compatibility-scale" parent="relational-property-scale" modified="Thu Feb  8 01:44:16 2018">
<SEM fltype="abstr-obj">
<FEATURES type="compatibility-scale" tangible="+" />
</SEM>
<ARGUMENT role="extent" optionality="optional" fltype="?!type" />
<ARGUMENT role="ground" optionality="optional" fltype="?!type" />
<ARGUMENT role="figure" optionality="required" fltype="?!type" />
<WORD name="compatibility" />
<MAPPING to="wordnet" name="compatibility%1:07:00::" url="http://wordnetweb.princeton.edu/perl/webwn?s=compatibility&amp;i=1&amp;o6=1" />
</ONTTYPE>
