<?xml version="1.0" encoding="UTF-8"?>
<!DOCTYPE ONTTYPE SYSTEM "onttype.dtd">
<ONTTYPE name="time-rate" parent="rate" modified="Wed Jun 22 01:43:35 2016">
<SEM fltype="abstr-obj">
<FEATURES type="time-rate" scale="rate-scale" measure-function="term" />
</SEM>
<ARGUMENT role="formal" optionality="essential" fltype="situation">
<FEATURES type="event-of-change" />
</ARGUMENT>
<ARGUMENT role="extent" optionality="essential" fltype="abstr-obj">
<FEATURES measure-function="value" scale="rate-scale" />
</ARGUMENT>
<ARGUMENT role="val" optionality="essential" fltype="abstr-obj">
<FEATURES measure-function="value" />
</ARGUMENT>
<ARGUMENT role="of" optionality="required" fltype="phys-obj" />
<WORD name="bandwidth" />
<WORD name="speed" />
<WORD name="velocity" />
<CHILD name="clock-speed" />
</ONTTYPE>
