<?xml version="1.0" encoding="UTF-8"?>
<?xml-stylesheet type="text/xsl" href="../style/onttype.xsl"?>
<!DOCTYPE ONTTYPE SYSTEM "onttype.dtd">
<ONTTYPE name="account" parent="value-cost" modified="Mon May  6 01:43:23 2019">
<SEM fltype="abstr-obj">
<FEATURES type="account" scale="money-scale" object-function="currency" measure-function="term" tangible="+" />
</SEM>
<ARGUMENT role="extent" optionality="required" fltype="abstr-obj">
<FEATURES scale="money-scale" object-function="currency" />
</ARGUMENT>
<ARGUMENT role="ground" optionality="required" fltype="abstr-obj">
<FEATURES scale="money-scale" object-function="currency" />
</ARGUMENT>
<ARGUMENT role="figure" optionality="essential" fltype="(? lof634 phys-obj abstr-obj)" />
<WORD name="account" />
<WORD name="fund" />
<WORD name="funding" />
<WORD name="grant" />
<CHILD name="account-payable" />
</ONTTYPE>
