<?xml version="1.0" encoding="UTF-8"?>
<!DOCTYPE ONTTYPE SYSTEM "onttype.dtd">
<ONTTYPE name="cause-to-move" parent="motion" modified="Thu Jan  5 01:43:37 2017">
<SEM fltype="situation">
<FEATURES type="cause-to-move" trajectory="+" cause="force" aspect="dynamic" container="-" information="mental-construct" intentional="-" />
</SEM>
<ARGUMENT role="extent" optionality="optional" fltype="abstr-obj">
<FEATURES type="quantity" />
</ARGUMENT>
<ARGUMENT role="result" optionality="optional" fltype="(? cau23125 situation abstr-obj phys-obj)" />
<ARGUMENT role="source" optionality="optional" fltype="?!type" />
<ARGUMENT role="beneficiary" optionality="optional" fltype="(? cau13126 phys-obj)" />
<ARGUMENT role="agent" optionality="essential" fltype="(? causetype3201 phys-obj situation abstr-obj)" />
<ARGUMENT role="affected" optionality="essential" fltype="(? ttype3225 phys-obj abstr-obj)" />
<WORD name="drive" />
<WORD name="throw" />
<MAPPING to="wordnet" name="drive%2:35:01::" url="http://wordnetweb.princeton.edu/perl/webwn?s=drive&amp;i=20&amp;o6=1" />
<MAPPING to="wordnet" name="drive%2:41:02::" url="http://wordnetweb.princeton.edu/perl/webwn?s=drive&amp;i=16&amp;o6=1" />
<CHILD name="dig" />
<CHILD name="herd" />
</ONTTYPE>
