<?xml version="1.0" encoding="UTF-8"?>
<!DOCTYPE ONTTYPE SYSTEM "onttype.dtd">
<ONTTYPE name="std" parent="disease" modified="Wed Dec 20 01:44:20 2017">
<SEM fltype="situation">
<FEATURES type="std" intentional="-" container="-" information="mental-construct" />
</SEM>
<ARGUMENT role="figure" optionality="optional" fltype="phys-obj">
<FEATURES origin="(? og2 human non-human-animal)" />
</ARGUMENT>
<WORD name="chlamydia" />
<WORD name="gonorrhea" />
<WORD name="herpes" />
<MAPPING to="wordnet" name="venereal_disease%1:26:00::" url="http://wordnetweb.princeton.edu/perl/webwn?s=venereal+disease&amp;i=0&amp;o6=1" />
</ONTTYPE>
