<?xml version="1.0" encoding="UTF-8"?>
<!DOCTYPE ONTTYPE SYSTEM "onttype.dtd">
<ONTTYPE name="establish" parent="create" modified="Tue Sep 27 01:44:21 2016">
<SEM fltype="situation">
<FEATURES type="establish" trajectory="-" cause="agentive" aspect="dynamic" container="-" information="mental-construct" intentional="-" />
</SEM>
<ARGUMENT role="result" optionality="optional" fltype="(? res343159 phys-obj abstr-obj)">
<FEATURES intentional="-" />
</ARGUMENT>
<ARGUMENT role="affected" optionality="optional" fltype="(? cau3a3124 situation abstr-obj phys-obj)" />
<ARGUMENT role="beneficiary" optionality="optional" fltype="(? cau13126 phys-obj)" />
<ARGUMENT role="affected-result" optionality="optional" fltype="(? neu23132 situation abstr-obj phys-obj)" />
<ARGUMENT role="agent" optionality="essential" fltype="(? cs3430 phys-obj abstr-obj)" />
<ARGUMENT role="manner" optionality="optional" fltype="?!type" />
<WORD name="base" />
<WORD name="establish" />
<WORD name="found" />
<WORD name="ground" />
<MAPPING to="wordnet" name="establish%2:41:00::" url="http://wordnetweb.princeton.edu/perl/webwn?s=establish&amp;i=0&amp;o6=1" />
<MAPPING to="wordnet" name="establish%2:36:00::" url="http://wordnetweb.princeton.edu/perl/webwn?s=establish&amp;i=1&amp;o6=1" />
<MAPPING to="wordnet" name="create%2:36:02::" url="http://wordnetweb.princeton.edu/perl/webwn?s=create&amp;i=1&amp;o6=1" />
<MAPPING to="wordnet" name="install%2:35:01::" url="http://wordnetweb.princeton.edu/perl/webwn?s=install&amp;i=2&amp;o6=1" />
</ONTTYPE>
