<?xml version="1.0" encoding="UTF-8"?>
<!DOCTYPE ONTTYPE SYSTEM "onttype.dtd">
<ONTTYPE name="poultry" parent="meat" modified="Mon Apr 23 01:42:53 2018">
<SEM fltype="phys-obj">
<FEATURES type="poultry" object-function="comestible" form="substance" mobility="non-self-moving" tangible="+" />
</SEM>
<WORD name="drumstick" />
<WORD name="giblet" />
<WORD name="gizzard" />
<CHILD name="chicken" />
<CHILD name="duck" />
<CHILD name="goose" />
<CHILD name="ostrich" />
<CHILD name="pheasant" />
<CHILD name="pigeon" />
<CHILD name="quail" />
<CHILD name="turkey" />
</ONTTYPE>
