<?xml version="1.0" encoding="UTF-8"?>
<?xml-stylesheet type="text/xsl" href="../style/lookup.xsl"?>
<!DOCTYPE WORD SYSTEM "word.dtd">
<WORD name="^s" modified="Sat Nov 26 01:45:05 2016">
<POS name="^s">
<CLASS onttype="^s" words="" ancestors="">
<FRAME desc="no-features-templ" />
</CLASS>
</POS>
<POS name="pro">
<CLASS onttype="person" words="^s,adolescent,adult,anybody,anyone,applicant,attendee,bidder,care giver,caregiver,donor,everybody,everyone,fellow,follower,grower,guest,guy,hers,herself,himself,host,human,hypochondriac,i,individual,king,licensee,lover,me,mine,my,myself,nobody,noone,one ^s,oneself,our,ours,ourselves,participant,party,person,persons,senior,somebody,someone,subordinate,subscriber,teen,teenager,theirs,us,we,who,whoever,whom,whose,y^,you,your,yours,yourself,yourselves,youth" ancestors="mammal,vertebrate,animal,organism,natural-object,phys-object,referential-sem,any-sem,root">
<FRAME desc="pronoun-plural-templ" />
</CLASS>
</POS>
<POS name="v">
<MORPH cat="past" to="was" />
<CLASS onttype="be" words="be" ancestors="in-relation,object-compare,event-of-state,situation-root,referential-sem,any-sem,root">
<FRAME desc="neutral-neutral-equal-templ" />
</CLASS>
<CLASS onttype="exists" words="be,exist" ancestors="be,in-relation,object-compare,event-of-state,situation-root,referential-sem,any-sem,root">
<FRAME desc="there-theme-templ (xp (% np (agr 3s)))" />
<FRAME desc="there-theme-templ (xp (% np (agr 3p)))" />
</CLASS>
<CLASS onttype="have-property" words="be,turn out" ancestors="event-of-state,situation-root,referential-sem,any-sem,root">
<FRAME desc="neutral-pred-xp-templ" />
<FRAME desc="expletive-theme-pred-templ (xp1 (% np (lex there)))" />
</CLASS>
<CLASS onttype="passive" words="be,get" ancestors="aux,situation-root,referential-sem,any-sem,root">
<FRAME desc="passive-templ" />
</CLASS>
<CLASS onttype="perfective" words="have" ancestors="aux,situation-root,referential-sem,any-sem,root">
<FRAME desc="perfective-templ" />
</CLASS>
<CLASS onttype="progressive" words="be" ancestors="aux,situation-root,referential-sem,any-sem,root">
<FRAME desc="prog-templ" />
</CLASS>
</POS>
</WORD>
