<?xml version="1.0" encoding="UTF-8"?>
<?xml-stylesheet type="text/xsl" href="../style/lookup.xsl"?>
<!DOCTYPE WORD SYSTEM "word.dtd">
<WORD name="assail" modified="Sun Jan 10 03:16:05 2016">
<POS name="v">
<MORPH cat="12s123pbase" to="assail" />
<MORPH cat="3s" to="assails" />
<MORPH cat="past" to="assailed" />
<MORPH cat="pastpart" to="assailed" />
<MORPH cat="ing" to="assailing" />
<CLASS onttype="attack" words="assail,assault,attack" ancestors="objective-influence,event-of-causation,event-of-action,event-of-change,situation-root,referential-sem,any-sem,root">
<FRAME desc="agent-affected-xp-templ" example="the smell assailed his senses" />
</CLASS>
<CLASS onttype="criticize" words="accurse,admonish,assail,assault,attack,belittle,calumniate,castigate,censure,chasten,chastise,chastize,chide,condemn,criticize,damn,decry,denigrate,denounce,deprecate,deride,disparage,excoriate,gibe,imprecate,lambaste,lampoon,malign,reprove,repudiate,revile,stigmatize,upbraid,vilify" ancestors="loaded-claim,representative,illocution,communication,agent-interaction,event-of-action,event-of-change,situation-root,referential-sem,any-sem,root">
<FRAME desc="agent-addressee-templ" />
</CLASS>
</POS>
</WORD>
