<?xml version="1.0" encoding="UTF-8"?>
<?xml-stylesheet type="text/xsl" href="../style/lookup.xsl"?>
<!DOCTYPE WORD SYSTEM "word.dtd">
<WORD name="backbite" modified="Wed Jul  5 15:31:51 2017">
<POS name="v">
<MORPH cat="12s123pbase" to="backbite" />
<MORPH cat="3s" to="backbites" />
<MORPH cat="past" to="backbit" />
<MORPH cat="pastpart" to="backbitten" />
<MORPH cat="ing" to="backbiting" />
<CLASS onttype="insult" words="backbite,blaspheme,curse,insult,mock,ridicule" ancestors="loaded-claim,representative,illocution,communication,agent-interaction,event-of-action,event-of-change,situation-root,referential-sem,any-sem,root">
<FRAME desc="agent-addressee-templ" />
</CLASS>
</POS>
</WORD>
