<?xml version="1.0" encoding="UTF-8"?>
<?xml-stylesheet type="text/xsl" href="../style/lookup.xsl"?>
<!DOCTYPE WORD SYSTEM "word.dtd">
<WORD name="break_up" modified="Wed Apr 28 01:47:18 2021">
<POS name="n">
<MORPH cat="nom" from="break_up" />
</POS>
<POS name="v">
<MORPH cat="12s123pbase" to="break_up" />
<MORPH cat="3s" to="breaks_up" />
<MORPH cat="past" to="broke_up" />
<MORPH cat="pastpart" to="broken_up" />
<MORPH cat="ing" to="breaking_up" />
<MORPH cat="nom" to="break_up" />
<CLASS onttype="social-separation" words="break up,breakup,divorce" ancestors="separation,event-of-causation,event-of-action,event-of-change,situation-root,referential-sem,any-sem,root">
<FRAME desc="agent-np-plural-templ" example="mr. and mrs. bee broke up." />
<FRAME desc="agent-affected-xp-pp-templ (xp (% pp (ptype (? t with))))" example="mrs. bee broke up with mr. bee." />
</CLASS>
</POS>
</WORD>
