<?xml version="1.0" encoding="UTF-8"?>
<?xml-stylesheet type="text/xsl" href="../style/lookup.xsl"?>
<!DOCTYPE WORD SYSTEM "word.dtd">
<WORD name="campaign" modified="Mon Apr 27 05:45:57 2020">
<POS name="n">
<MORPH cat="sing" to="campaign" />
<CLASS onttype="campaign" words="campaign" ancestors="event-type,situation-root,referential-sem,any-sem,root">
<FRAME desc="count-pred-templ" />
</CLASS>
<CLASS onttype="commitment" words="agenda,campaign,itinerary,timeline" ancestors="ps-object,mental-construction,tangible-abstract-object,abstract-object,referential-sem,any-sem,root">
<FRAME desc="count-pred-templ" />
</CLASS>
</POS>
<POS name="v">
<MORPH cat="12s123pbase" to="campaign" />
<MORPH cat="3s" to="campaigns" />
<MORPH cat="past" to="campaigned" />
<MORPH cat="pastpart" to="campaigned" />
<MORPH cat="ing" to="campaigning" />
<CLASS onttype="fighting" words="campaign,contend,defend,fight,struggle" ancestors="agent-interaction,event-of-action,event-of-change,situation-root,referential-sem,any-sem,root">
<FRAME desc="agent-neutral-xp-templ" example="he campaigned the proposal" />
<FRAME desc="agent-templ" example="he campaigned (with/for/against them)" />
<FRAME desc="agent-formal-subjcontrol-templ (xp (% cp (ctype s-to)))" example="he campaigned to establish the area" />
</CLASS>
</POS>
</WORD>
