<?xml version="1.0" encoding="UTF-8"?>
<?xml-stylesheet type="text/xsl" href="../style/lookup.xsl"?>
<!DOCTYPE WORD SYSTEM "word.dtd">
<WORD name="call_off" modified="Thu Aug  1 01:44:30 2019">
<POS name="v">
<MORPH cat="12s123pbase" to="call_off" />
<MORPH cat="3s" to="calls_off" />
<MORPH cat="past" to="called_off" />
<MORPH cat="pastpart" to="called_off" />
<MORPH cat="pastpart" to="called" />
<MORPH cat="ing" to="calling_off" />
<CLASS onttype="cancel" words="call off,cancel,forget,scratch" ancestors="cause-action,acting,event-of-action,event-of-change,situation-root,referential-sem,any-sem,root">
<FRAME desc="agent-affected-templ" example="call off the engagement" />
</CLASS>
</POS>
</WORD>
