<?xml version="1.0" encoding="UTF-8"?>
<?xml-stylesheet type="text/xsl" href="../style/lookup.xsl"?>
<!DOCTYPE WORD SYSTEM "word.dtd">
<WORD name="demolish" modified="Sun Mar 20 03:16:21 2016">
<POS name="v">
<MORPH cat="12s123pbase" to="demolish" />
<MORPH cat="3s" to="demolishes" />
<MORPH cat="past" to="demolished" />
<MORPH cat="pastpart" to="demolished" />
<MORPH cat="ing" to="demolishing" />
<MORPH cat="nom" to="demolition" />
<CLASS onttype="destroy" words="abort,annihilate,blitz,decimate,demolish,desecrate,destroy,devastate,disfigure,efface,eradicate,exterminate,extirpate,kill,maim,mangle,murder,mutilate,obliterate,ravage,raze,ruin,slaughter,waste,wreck" ancestors="change-state,change,event-of-causation,event-of-action,event-of-change,situation-root,referential-sem,any-sem,root">
<FRAME desc="agent-affected-xp-templ" />
</CLASS>
<CLASS onttype="evoke-excitement" words="agitate,demolish,devastate,energize,enliven,excite,overawe,overwhelm,recharge,refresh,rejuvenate,roil,shake,stir,strike,wow" ancestors="evoke-emotion,affect-experiencer,event-of-causation,event-of-action,event-of-change,situation-root,referential-sem,any-sem,root">
<FRAME desc="agent-affected-xp-templ" />
</CLASS>
</POS>
</WORD>
