<?xml version="1.0" encoding="UTF-8"?>
<?xml-stylesheet type="text/xsl" href="../style/lookup.xsl"?>
<!DOCTYPE WORD SYSTEM "word.dtd">
<WORD name="deteriorate" modified="Fri Jul 28 01:45:51 2017">
<POS name="v">
<MORPH cat="12s123pbase" to="deteriorate" />
<MORPH cat="3s" to="deteriorates" />
<MORPH cat="past" to="deteriorated" />
<MORPH cat="pastpart" to="deteriorated" />
<MORPH cat="ing" to="deteriorating" />
<CLASS onttype="deteriorate" words="corrode,decay,degrade,deteriorate,erode,molder,rot,rust,stagnate,tarnish,wilt,worsen" ancestors="continuous-change,transformation,change,event-of-causation,event-of-action,event-of-change,situation-root,referential-sem,any-sem,root">
<FRAME desc="agent-affected-xp-templ" />
<FRAME desc="affected-templ" example="the structure deteriorated" />
</CLASS>
</POS>
</WORD>
