<?xml version="1.0" encoding="UTF-8"?>
<?xml-stylesheet type="text/xsl" href="../style/lookup.xsl"?>
<!DOCTYPE WORD SYSTEM "word.dtd">
<WORD name="film" modified="Sun Jul 10 01:43:33 2016">
<POS name="n">
<MORPH cat="sing" to="film" />
<MORPH cat="plur" to="films" />
<CLASS onttype="material" words="aluminium,aluminum,brick,cloth,copper,crystal,fabric,fiber,film,filmstrip,leather,material,metal,paper,plastic,rubber,steel,tape,tar,titanium,wood" ancestors="phys-object,referential-sem,any-sem,root">
<FRAME desc="count-pred-templ" example="35mm film" />
</CLASS>
</POS>
<POS name="v">
<MORPH cat="12s123pbase" to="film" />
<MORPH cat="3s" to="films" />
<MORPH cat="past" to="filmed" />
<MORPH cat="pastpart" to="filmed" />
<MORPH cat="ing" to="filming" />
<CLASS onttype="record" words="chronicle,film,log,microfilm,note,photocopy,photograph,record,register,tape,transcribe" ancestors="event-of-action,event-of-change,situation-root,referential-sem,any-sem,root">
<FRAME desc="agent-theme-xp-templ" />
</CLASS>
</POS>
</WORD>
