<?xml version="1.0" encoding="UTF-8"?>
<?xml-stylesheet type="text/xsl" href="../style/lookup.xsl"?>
<!DOCTYPE WORD SYSTEM "word.dtd">
<WORD name="gleam" modified="Thu Apr 19 01:44:59 2018">
<POS name="v">
<MORPH cat="12s123pbase" to="gleam" />
<MORPH cat="3s" to="gleams" />
<MORPH cat="past" to="gleamed" />
<MORPH cat="pastpart" to="gleamed" />
<MORPH cat="ing" to="gleaming" />
<CLASS onttype="location-of-light" words="gleam,glimmer,glint,glow,shine,sparkle" ancestors="event-of-action,event-of-change,situation-root,referential-sem,any-sem,root">
<FRAME desc="agent-templ" />
</CLASS>
</POS>
</WORD>
