<?xml version="1.0" encoding="UTF-8"?>
<?xml-stylesheet type="text/xsl" href="../style/lookup.xsl"?>
<!DOCTYPE WORD SYSTEM "word.dtd">
<WORD name="go" modified="Wed Mar 22 01:44:26 2017">
<POS name="n">
<CLASS onttype="board-game" words="checkers,chess,go" ancestors="game,competition,event-defined-by-activity,event-type,situation-root,referential-sem,any-sem,root">
<FRAME desc="mass-pred-templ" />
</CLASS>
</POS>
<POS name="v">
<MORPH cat="12s123pbase" to="go" />
<MORPH cat="3s" to="goes" />
<MORPH cat="past" to="went" />
<MORPH cat="pastpart" to="gone" />
<MORPH cat="ing" to="going" />
<CLASS onttype="become" words="become,come,fall,get,go,grow" ancestors="event-of-undergoing-action,event-of-change,situation-root,referential-sem,any-sem,root">
<FRAME desc="affected-pred-templ" example="the meat has gone bad" />
</CLASS>
<CLASS onttype="execute" words="act,conduct,do,execute,go,perform,redo,run" ancestors="cause-effect,acting,event-of-action,event-of-change,situation-root,referential-sem,any-sem,root">
<FRAME desc="agent-effect-subjcontrol-templ (xp (% vp (vform ing)))" example="he went jogging" />
<FRAME desc="agent-effect-xp-templ (xp (% pp (ptype (? pt for))))" example="he went for a walk" />
</CLASS>
<CLASS onttype="move" words="go,mobilize,move,navigate,present,travel" ancestors="motion,event-of-causation,event-of-action,event-of-change,situation-root,referential-sem,any-sem,root">
<FRAME desc="agent-templ" example="go to amazon dot com; go by the store" />
</CLASS>
<CLASS onttype="occurring" words="befall,come,ensue,eventuate,go,happen,occur,recur,transpire,turn out" ancestors="situation-root,referential-sem,any-sem,root">
<FRAME desc="neutral-templ" example="the interview went well" />
</CLASS>
<CLASS onttype="should-be-at" words="belong,go" ancestors="be-at,position,event-of-state,situation-root,referential-sem,any-sem,root">
<FRAME desc="neutral-location-templ" example="this goes here; the title goes in the textbox" />
</CLASS>
<CLASS onttype="startoff-begin-commence-start" words="begin,commence,go,start,start off" ancestors="start,cause-effect,acting,event-of-action,event-of-change,situation-root,referential-sem,any-sem,root">
<FRAME desc="agent-effect-subjcontrol-templ (xp (% cp (ctype (? ct s-and))))" example="go to/and fix the power lines" />
<FRAME desc="agent-effect-subjcontrol-templ (xp (% vp (vform base) (complex -)))" example="go find it" />
</CLASS>
<CLASS onttype="undergo-action" words="go,happen,undergo" ancestors="event-of-undergoing-action,event-of-change,situation-root,referential-sem,any-sem,root">
<FRAME desc="affected-templ" example="i kept going" />
</CLASS>
</POS>
</WORD>
