<?xml version="1.0" encoding="UTF-8"?>
<?xml-stylesheet type="text/xsl" href="../style/lookup.xsl"?>
<!DOCTYPE WORD SYSTEM "word.dtd">
<WORD name="guess" modified="Thu Dec 21 01:42:51 2017">
<POS name="n">
<CLASS onttype="information" words="" ancestors="information-function-object,function-object,tangible-abstract-object,abstract-object,referential-sem,any-sem,root">
<FRAME desc="count-pred-templ" />
</CLASS>
</POS>
<POS name="v">
<CLASS onttype="determine" words="" ancestors="cogitation,change-awareness,event-of-awareness,event-of-change,situation-root,referential-sem,any-sem,root">
<FRAME desc="agent-theme-xp-templ" example="he guessed the answer" />
</CLASS>
<CLASS onttype="suppose" words="" ancestors="attitude-of-belief,awareness,event-of-experience,event-of-state,situation-root,referential-sem,any-sem,root">
<FRAME desc="experiencer-theme-xp-templ (xp (% cp (ctype s-finite)))" example="i guess that we could try that" />
<FRAME desc="experiencer-templ" example="i guess" />
</CLASS>
</POS>
</WORD>
