<?xml version="1.0" encoding="UTF-8"?>
<?xml-stylesheet type="text/xsl" href="../style/lookup.xsl"?>
<!DOCTYPE WORD SYSTEM "word.dtd">
<WORD name="line" modified="Thu Dec 21 01:42:52 2017">
<POS name="n">
<CLASS onttype="graphic-symbol" words="" ancestors="symbolic-representation,phys-representation,phys-object,referential-sem,any-sem,root">
<FRAME desc="count-pred-templ" example="the red line on the map" />
</CLASS>
<CLASS onttype="grouping" words="" ancestors="version,kind,abstract-object-nontemporal,abstract-object,referential-sem,any-sem,root">
<FRAME desc="count-pred-templ" example="a product line" />
</CLASS>
<CLASS onttype="linear-grouping" words="" ancestors="sequence,group-object,phys-object,referential-sem,any-sem,root">
<FRAME desc="other-reln-templ" example="a line of blocks" />
</CLASS>
</POS>
</WORD>
