<?xml version="1.0" encoding="UTF-8"?>
<?xml-stylesheet type="text/xsl" href="../style/lookup.xsl"?>
<!DOCTYPE WORD SYSTEM "word.dtd">
<WORD name="other" modified="Sun Jan 17 03:17:10 2016">
<POS name="adj">
<MORPH cat="nil" to="other" />
<CLASS onttype="identity-val" words="else,other,the same" ancestors="similarity-val,relation,abstract-object-property,abstract-object,referential-sem,any-sem,root">
<FRAME desc="adj-theme-templ" />
</CLASS>
</POS>
<POS name="n">
<MORPH cat="sing" to="other" />
<MORPH cat="plur" to="others" />
<CLASS onttype="referential-sem" words="^em,another,anything,each other,everything,it,item,its,itself,nothing,on which,one,one another,other,point,something,that,their,them,themselves,these,they,thing,thingy,this,those,what,whatever,which,whichever,whose" ancestors="any-sem,root">
<FRAME desc="count-pred-templ" />
</CLASS>
</POS>
</WORD>
