<?xml version="1.0" encoding="UTF-8"?>
<?xml-stylesheet type="text/xsl" href="../style/lookup.xsl"?>
<!DOCTYPE WORD SYSTEM "word.dtd">
<WORD name="pleasant" modified="Thu Jun 22 01:46:58 2017">
<POS name="adj">
<MORPH cat="nil" to="pleasant" />
<MORPH cat="ly" to="pleasantly" />
<CLASS onttype="pleasant" words="pleasant" ancestors="pos-soft-emotional-val,pos-emotional-val,emotional-val,psychological-property-val,property-val,domain-property,abstract-object,referential-sem,any-sem,root">
<FRAME desc="central-adj-templ" example="a pleasant story" />
<FRAME desc="adj-purpose-templ" example="a wall pleasant for climbing" />
</CLASS>
</POS>
</WORD>
