<?xml version="1.0" encoding="UTF-8"?>
<?xml-stylesheet type="text/xsl" href="../style/lookup.xsl"?>
<!DOCTYPE WORD SYSTEM "word.dtd">
<WORD name="provide" modified="Thu Oct 22 01:44:57 2020">
<POS name="v">
<MORPH cat="12s123pbase" to="provide" />
<MORPH cat="3s" to="provides" />
<MORPH cat="past" to="provided" />
<MORPH cat="pastpart" to="provided" />
<MORPH cat="ing" to="providing" />
<MORPH cat="nom" to="provision" />
<CLASS onttype="supply" words="arm,equip,furnish,issue,provide,serve,supply" ancestors="giving,relinquish,event-of-causation,event-of-action,event-of-change,situation-root,referential-sem,any-sem,root">
<FRAME desc="agent-affected-affectedr-xp-optional-templ" example="provide the food (to him)" />
<FRAME desc="agent-affectedr-affected-xp-np-templ (xp (% pp (ptype with)))" example="provide him with the food" />
</CLASS>
</POS>
</WORD>
