<?xml version="1.0" encoding="UTF-8"?>
<?xml-stylesheet type="text/xsl" href="../style/lookup.xsl"?>
<!DOCTYPE WORD SYSTEM "word.dtd">
<WORD name="remark" modified="Wed Jun 22 01:45:23 2016">
<POS name="n">
<MORPH cat="nom" from="remark" />
<MORPH cat="sing" to="remark" />
<MORPH cat="plur" to="remarks" />
<CLASS onttype="say" words="articulate,comment,express,mention,remark,say,speak,utter,voice" ancestors="communication,agent-interaction,event-of-action,event-of-change,situation-root,referential-sem,any-sem,root">
<FRAME desc="count-subcat-that-optional-templ" example="the remark that he left" />
</CLASS>
</POS>
<POS name="v">
<MORPH cat="12s123pbase" to="remark" />
<MORPH cat="3s" to="remarks" />
<MORPH cat="past" to="remarked" />
<MORPH cat="pastpart" to="remarked" />
<MORPH cat="ing" to="remarking" />
<MORPH cat="nom" to="remark" />
<CLASS onttype="say" words="articulate,comment,express,mention,remark,say,speak,utter,voice" ancestors="communication,agent-interaction,event-of-action,event-of-change,situation-root,referential-sem,any-sem,root">
<FRAME desc="agent-theme-xp-templ (xp (% cp (ctype (? c s-finite))))" example="he remarked that three teams are going to delta" />
<FRAME desc="agent-about-theme-addressee-optional-templ" example="he remarked about it [to her]" />
</CLASS>
</POS>
</WORD>
