<?xml version="1.0" encoding="UTF-8"?>
<?xml-stylesheet type="text/xsl" href="../style/lookup.xsl"?>
<!DOCTYPE WORD SYSTEM "word.dtd">
<WORD name="rest" modified="Sat Dec 10 01:46:37 2016">
<POS name="n">
<MORPH cat="sing" to="rest" />
<MORPH cat="plur" to="rests" />
<CLASS onttype="part" words="accessory,branch,chunk,composite,element,extension,factor,increment,installment,module,part,piece,portion,rest,section,segment,subsection" ancestors="referential-sem,any-sem,root">
<FRAME desc="gen-part-of-reln-templ" />
<FRAME desc="count-pred-templ" />
</CLASS>
</POS>
<POS name="v">
<MORPH cat="12s123pbase" to="rest" />
<MORPH cat="3s" to="rests" />
<MORPH cat="past" to="rested" />
<MORPH cat="pastpart" to="rested" />
<MORPH cat="ing" to="resting" />
<CLASS onttype="be-at-loc" words="dangle,hang,lie,localise,localize,perch,rest,sit,stand,suspend" ancestors="be-at,position,event-of-state,situation-root,referential-sem,any-sem,root">
<FRAME desc="neutral-location-templ" />
</CLASS>
</POS>
</WORD>
