<?xml version="1.0" encoding="UTF-8"?>
<?xml-stylesheet type="text/xsl" href="../style/lookup.xsl"?>
<!DOCTYPE WORD SYSTEM "word.dtd">
<WORD name="retry" modified="Tue Jan 31 01:44:53 2017">
<POS name="v">
<MORPH cat="12s123pbase" to="retry" />
<MORPH cat="3s" to="retries" />
<MORPH cat="past" to="retried" />
<MORPH cat="pastpart" to="retried" />
<MORPH cat="ing" to="retrying" />
<CLASS onttype="try-again" words="retry" ancestors="try,cause-effect,acting,event-of-action,event-of-change,situation-root,referential-sem,any-sem,root">
<FRAME desc="agent-effect-xp-templ" example="retry this option" />
</CLASS>
</POS>
</WORD>
