<?xml version="1.0" encoding="UTF-8"?>
<?xml-stylesheet type="text/xsl" href="../style/lookup.xsl"?>
<!DOCTYPE WORD SYSTEM "word.dtd">
<WORD name="roll" modified="Sun Feb 19 01:44:47 2017">
<POS name="n">
<MORPH cat="sing" to="roll" />
<MORPH cat="plur" to="rolls" />
<CLASS onttype="bagels-biscuits" words="bagel,biscuit,crepe,dinner roll,english muffin,french roll,kaiser roll,muffin,pancake,roll" ancestors="baked-goods,prepared,food,substance,material,phys-object,referential-sem,any-sem,root">
<FRAME desc="count-pred-templ" />
</CLASS>
</POS>
<POS name="v">
<MORPH cat="12s123pbase" to="roll" />
<MORPH cat="3s" to="rolls" />
<MORPH cat="past" to="rolled" />
<MORPH cat="pastpart" to="rolled" />
<MORPH cat="ing" to="rolling" />
<CLASS onttype="roll" words="roll" ancestors="move,motion,event-of-causation,event-of-action,event-of-change,situation-root,referential-sem,any-sem,root">
<FRAME desc="affected-templ" />
<FRAME desc="agent-templ" />
</CLASS>
<CLASS onttype="rotate" words="flip,flip over,reverse,revolve,roll,rotate,spin,turn,twirl,twist,whirl,wind" ancestors="event-of-causation,event-of-action,event-of-change,situation-root,referential-sem,any-sem,root">
<FRAME desc="agent-affected-xp-templ" />
</CLASS>
<CLASS onttype="select" words="check,choose,go for,go with,mark,pick,pick out,roll,select,specify,uncheck,vote" ancestors="choosing,intentionally-act,event-of-action,event-of-change,situation-root,referential-sem,any-sem,root">
<FRAME desc="agent-theme-xp-templ (xp (% pp (ptype with)))" example="let's roll with that one" />
</CLASS>
</POS>
</WORD>
