<?xml version="1.0" encoding="UTF-8"?>
<?xml-stylesheet type="text/xsl" href="../style/lookup.xsl"?>
<!DOCTYPE WORD SYSTEM "word.dtd">
<WORD name="subtract" modified="Sat Sep 16 01:49:21 2017">
<POS name="v">
<MORPH cat="12s123pbase" to="subtract" />
<MORPH cat="3s" to="subtracts" />
<MORPH cat="past" to="subtracted" />
<MORPH cat="pastpart" to="subtracted" />
<MORPH cat="ing" to="subtracting" />
<CLASS onttype="calc-subtract" words="deduct,subtract" ancestors="calculation,becoming-aware-of-value,scrutiny,cogitation,change-awareness,event-of-awareness,event-of-change,situation-root,referential-sem,any-sem,root">
<FRAME desc="agent-theme-theme-optional-templ (xp (% pp (ptype from)))" example="subtract five dollars [from the price]; subtract 5 [ from sin(x) ]" />
</CLASS>
<CLASS onttype="cause-out-of" words="dig out,egress,extract,subtract,take out,withdraw" ancestors="cause-come-from,event-of-causation,event-of-action,event-of-change,situation-root,referential-sem,any-sem,root">
<FRAME desc="agent-affected-source-optional-templ" example="subtract the wireless card [from the order]" />
</CLASS>
</POS>
</WORD>
