<?xml version="1.0" encoding="UTF-8"?>
<?xml-stylesheet type="text/xsl" href="../style/lookup.xsl"?>
<!DOCTYPE WORD SYSTEM "word.dtd">
<WORD name="take_a_chance" modified="Thu Sep 21 01:49:19 2017">
<POS name="v">
<MORPH cat="12s123pbase" to="take_a_chance" />
<MORPH cat="3s" to="takes_a_chance" />
<MORPH cat="past" to="took_a_chance" />
<MORPH cat="pastpart" to="taken_a_chance" />
<MORPH cat="ing" to="taking_a_chance" />
<CLASS onttype="rely" words="bank,bargain,bet,count,depend,gamble,rely,take a chance,wager" ancestors="believe-source,awareness,event-of-experience,event-of-state,situation-root,referential-sem,any-sem,root">
<FRAME desc="agent-neutral-xp-templ (xp (% pp (ptype on)))" />
</CLASS>
</POS>
</WORD>
