<?xml version="1.0" encoding="UTF-8"?>
<?xml-stylesheet type="text/xsl" href="../style/lookup.xsl"?>
<!DOCTYPE WORD SYSTEM "word.dtd">
<WORD name="tolerably" modified="Sun Dec 31 01:44:40 2017">
<POS name="adv">
<CLASS onttype="degree-modifier-med" words="about,bearably,fairly,halfway,kind of,kinda,moderately,practically,pretty,pretty much,quite,rather,right,sort of,sorta,tolerably" ancestors="degree-modifier,modifier,predicate,abstract-object,referential-sem,any-sem,root">
<FRAME desc="adj-adv-operator-templ" />
</CLASS>
<CLASS onttype="tolerable-val" words="bearable,supportable,tolerable,tolerably" ancestors="tolerability-val,evaluation-attribute-val,property-val,domain-property,abstract-object,referential-sem,any-sem,root">
<FRAME desc="adj-operator-templ" example="his ankles are tolerably swollen" />
<FRAME desc="pred-vp-templ" example="his ankles swelled tolerably" />
</CLASS>
</POS>
</WORD>
