<?xml version="1.0" encoding="UTF-8"?>
<?xml-stylesheet type="text/xsl" href="../style/lookup.xsl"?>
<!DOCTYPE WORD SYSTEM "word.dtd">
<WORD name="true" modified="Sun Oct 25 21:36:40 2015">
<POS name="adj">
<MORPH cat="nil" to="true" />
<CLASS onttype="actual" words="actual,real,realistic,so,true" ancestors="actuality-val,physical-property-val,property-val,abstract-object-property,abstract-object,referential-sem,any-sem,root">
<FRAME desc="central-adj-templ" example="a true friend" />
</CLASS>
<CLASS onttype="evaluation-val" words="right,true,wrong" ancestors="relation,abstract-object-property,abstract-object,referential-sem,any-sem,root">
<FRAME desc="adj-co-theme-templ (xp (% pp (ptype for)))" example="that's true [for him]" />
</CLASS>
</POS>
</WORD>
