<?xml version="1.0" encoding="UTF-8"?>
<?xml-stylesheet type="text/xsl" href="../style/lookup.xsl"?>
<!DOCTYPE WORD SYSTEM "word.dtd">
<WORD name="uncover" modified="Thu May 24 01:45:32 2018">
<POS name="v">
<MORPH cat="12s123pbase" to="uncover" />
<MORPH cat="3s" to="uncovers" />
<MORPH cat="past" to="uncoverred" />
<MORPH cat="pastpart" to="uncoverred" />
<MORPH cat="ing" to="uncoverring" />
<CLASS onttype="expose" words="expose,uncover" ancestors="show,communication,agent-interaction,event-of-action,event-of-change,situation-root,referential-sem,any-sem,root">
<FRAME desc="agent-affected-xp-templ" example="uncover the source" />
</CLASS>
</POS>
</WORD>
